odoo/addons/l10n_it_payment_reason/README.rst
odoo/addons/l10n_it_payment_reason/__init__.py
odoo/addons/l10n_it_payment_reason/__manifest__.py
odoo/addons/l10n_it_payment_reason/data/payment_reason_data.xml
odoo/addons/l10n_it_payment_reason/i18n/it.po
odoo/addons/l10n_it_payment_reason/i18n/l10n_it_payment_reason.pot
odoo/addons/l10n_it_payment_reason/models/__init__.py
odoo/addons/l10n_it_payment_reason/models/payment_reason.py
odoo/addons/l10n_it_payment_reason/readme/CONFIGURE.md
odoo/addons/l10n_it_payment_reason/readme/CONTRIBUTORS.md
odoo/addons/l10n_it_payment_reason/readme/DESCRIPTION.md
odoo/addons/l10n_it_payment_reason/readme/USAGE.md
odoo/addons/l10n_it_payment_reason/security/ir.model.access.csv
odoo/addons/l10n_it_payment_reason/static/description/icon.png
odoo/addons/l10n_it_payment_reason/static/description/index.html
odoo/addons/l10n_it_payment_reason/tests/__init__.py
odoo/addons/l10n_it_payment_reason/tests/test_reason.py
odoo/addons/l10n_it_payment_reason/views/payment_reason_view.xml
odoo_addon_l10n_it_payment_reason-16.0.1.0.0.9.dist-info/METADATA
odoo_addon_l10n_it_payment_reason-16.0.1.0.0.9.dist-info/WHEEL
odoo_addon_l10n_it_payment_reason-16.0.1.0.0.9.dist-info/top_level.txt
odoo_addon_l10n_it_payment_reason-16.0.1.0.0.9.dist-info/RECORD
